{"g6OQDAOCJzCBtynstumJgw==":"mbr-1920x1280.jpg","Hlq5JRJRcVszU5q7BGJg4Q==":"mbr-1076x713.jpg","NsApm2Zkp5v6zCa1y6HWRg==":"mbr-1076x636.jpg","ax33qN0PqTJokzSTua0Ptg==":"mbr-1-1076x713.jpg","XGj5P5UVLi42Kxf57LY0Sw==":"mbr-1076x605.jpg","9CitA5DSR+XmcQB3s0wVqg==":"mbr-1920x1276.jpg","wnLcF7KnE2R1m2B4YH9PIQ==":"mbr-1-1076x605.jpg","sjywLOkfaAohQbtsgRb9SA==":"mbr-1076x673.jpg","L3ikXKhNmzMyjI3St05a3A==":"mbr-1-1920x1280.jpg","EWz1+7V+FSCrD58ta0EdwQ==":"mbr-1920x924.jpg","W4Ibva8uuO4E10I0hYLXrg==":"mbr-1836x1263.png","pP7Vjj+wbk9o+nIjwPu7oQ==":"mbr-1836x1224.jpg","2k7Qse9jI5u6AswpAylxfA==":"mbr-1836x1225.jpg","U6/p0mzWup58zAIYlaNZbg==":"mbr-1076x717.jpg","1b9bJOg+KKIr1AnMVWMAAg==":"mbr-1836x1087.jpg","B3fvKdDPs2pR5NbpBBM8nQ==":"mbr-1076x609.jpg","lkvSp80pI3fQzaA0Fi74Uw==":"mbr-1-1836x1224.jpg","F4xUoZOUjnTWhUn9vmdz2w==":"mbr-1-1076x717.jpg","7wqKIdgElID8o1/PKQigvg==":"mbr-2-1076x717.jpg","Sz/CswctA8CTEOlQ6536yA==":"mbr-1076x718.jpg"}